{"AP_VERSION": "G960FXXU7DTAA", "CSC_VERSION": "G960FOXM7DTAC", "ANDROID_VERSION": "Q(Android 10)", "BIT": "7", "SIZE": "4.68 GB  Full Files", "MD5": "1d1657cd805e686613c483117b5d3859", "CSC": "   XFA - South Africa  ", "BUILD_DATE": "20200122124902", "ADD_DATE": "2020-02-08 05:28:43", "SECURITY": "PATCH LEVEL 2020-01-01", "DOWNLOADED": "223", "Remove": "FRP", "original_filename": "Samfw.com_SM-G960F_XFA_G960FXXU7DTAA_fac.zip", "timestamp": 1680155283.886754, "human_download_time": "2023-03-30T07:48:03.886771"}