{"AP_VERSION": "G960FXXUHFVB4", "CSC_VERSION": "G960FOXMHFVB4", "ANDROID_VERSION": "Q(Android 10)", "BIT": "H", "SIZE": "4.71 GB  Full Files", "MD5": "53e3f9364c716471e2bd1945c70d53e2", "CSC": "   XFA - South Africa  ", "BUILD_DATE": "20220225083451", "ADD_DATE": "2022-03-11 18:54:44", "SECURITY": "PATCH LEVEL 2022-03-01", "DOWNLOADED": "4785", "Remove": "FRP", "original_filename": "Samfw.com_SM-G960F_XFA_G960FXXUHFVB4_fac.zip", "timestamp": 1680119249.069209, "human_download_time": "2023-03-29T21:47:29.069213"}